famCircle/Ks.py
famCircle/Ks_block.py
famCircle/WGD_family.py
famCircle/__init__.py
famCircle/bez.py
famCircle/circle.py
famCircle/circle_all.py
famCircle/circle_family.py
famCircle/circle_family1.py
famCircle/conf.ini
famCircle/dispersed.py
famCircle/family_pair.py
famCircle/filterWGD.py
famCircle/filter_unit.py
famCircle/hmmer.py
famCircle/inner.py
famCircle/line.py
famCircle/msa.py
famCircle/outer.py
famCircle/part.py
famCircle/part_out.py
famCircle/proximal.py
famCircle/run.py
famCircle/screen.py
famCircle/tandem.py
famCircle/trd.py
famCircle/tree.py
famCircle/typing.py
famCircle/example/Ks.conf
famCircle/example/Ks_block.conf
famCircle/example/WGD_family.conf
famCircle/example/__init__.py
famCircle/example/circle.conf
famCircle/example/circle_all.conf
famCircle/example/circle_family.conf
famCircle/example/dispersed.conf
famCircle/example/family_pair.conf
famCircle/example/filterWGD.conf
famCircle/example/filter_unit.conf
famCircle/example/hmmer.conf
famCircle/example/inner.conf
famCircle/example/line.conf
famCircle/example/msa.conf
famCircle/example/outer.conf
famCircle/example/part.conf
famCircle/example/part_out.conf
famCircle/example/proximal.conf
famCircle/example/screen.conf
famCircle/example/tandem.conf
famCircle/example/trd.conf
famCircle/example/tree.conf
famCircle/example/typing.conf
famCircle-0.2.5.dist-info/LICENSE
famCircle-0.2.5.dist-info/METADATA
famCircle-0.2.5.dist-info/WHEEL
famCircle-0.2.5.dist-info/entry_points.txt
famCircle-0.2.5.dist-info/top_level.txt
famCircle-0.2.5.dist-info/zip-safe
famCircle-0.2.5.dist-info/RECORD
