Metadata-Version: 2.1
Name: famCircle
Version: 0.2.5
Summary: famCircle
Home-page: UNKNOWN
Author: charles_kiko
Author-email: charles_kiko@163.com
License: BSD License
Platform: UNKNOWN
Classifier: Intended Audience :: Science/Research
Classifier: Programming Language :: Python :: 3
Classifier: License :: OSI Approved :: BSD License
Classifier: Operating System :: OS Independent
Requires-Dist: pandas
Requires-Dist: numpy
Requires-Dist: biopython
Requires-Dist: matplotlib
Requires-Dist: scipy
Requires-Dist: interval
Requires-Dist: seaborn
Requires-Dist: tqdm
